Workbook

Sheet Budget
B1: Deer Ridge Apartments | C1: (drnd) | E1: Year 1 Budget · Sep-26 – Aug-27
B3: Units: | C3: 163 | D3: Total Income - | E3: =R95 | F3: Total Expense - | G3: =R318 | H3: NOI - | I3: =R319 | J3: Interest - | K3: =R324 | L3: Principal - | M3: =ABS(R388+R389+R390) | N3: Cash Flow - | O3: =I3-K3-M3 | P3: Cash on Cash - | Q3: =IF($C$4>0,O3/$C$4,"")
B4: Capital: | C4: 0
A6: GL Code | B6: GL Name | C6: Notes | D6: Driver | E6: Sep-26 | F6: Oct-26 | G6: Nov-26 | H6: Dec-26 | I6: Jan-27 | J6: Feb-27 | K6: Mar-27 | L6: Apr-27 | M6: May-27 | N6: Jun-27 | O6: Jul-27 | P6: Aug-27 | R6: Total Year 1 Budget | T6: Year 1 UW Budget | U6: Minot Budget at 163 units | X6: Total Per Unit | Y6: Per Unit / Month | Z6: Notes for Budget Upload
A7: 4991 | B7: INCOME
A8: 4992 | B8: RENTAL INCOME
A9: 4993 | B9: NET GROSS POTENTIAL RENT
A10: 4994 | B10: TENANT GROSS POTENTIAL | D10: rent roll GPR | E10: 276505 | F10: 276505 | G10: 276505 | H10: 276505 | I10: 276505 | J10: 276505 | K10: 276505 | L10: 276505 | M10: 276505 | N10: 276505 | O10: 276505 | P10: 276505 | R10: =SUM(E10:P10) | T10: 3219092.9 | U10: 2810093.9 | X10: =R10/$C$3 | Y10: =R10/$C$3/12
A11: 4995 | B11: HAP CONTRACT RENT | R11: =SUM(E11:P11) | X11: =R11/$C$3 | Y11: =R11/$C$3/12
A12: 4996 | B12: HAP VOUCHER RENT | R12: =SUM(E12:P12) | U12: 26592.81 | X12: =R12/$C$3 | Y12: =R12/$C$3/12
A13: 5003 | B13: LOSS/GAIN TO LEASE | D13: LTL burnoff | E13: -24280.78 | F13: -22502.47 | G13: -20724.17 | H13: -18945.87 | I13: -17167.56 | J13: -15389.26 | K13: -13610.95 | L13: -11832.64 | M13: -10054.34 | N13: -8276.03 | O13: -6497.72 | P13: -4719.41 | R13: =SUM(E13:P13) | T13: -80477.323 | U13: -376509.1 | X13: =R13/$C$3 | Y13: =R13/$C$3/12
A14: 5004 | B14: TOTAL NET GROSS POTENTIAL RENT | E14: =SUM(E10:E13) | F14: =SUM(F10:F13) | G14: =SUM(G10:G13) | H14: =SUM(H10:H13) | I14: =SUM(I10:I13) | J14: =SUM(J10:J13) | K14: =SUM(K10:K13) | L14: =SUM(L10:L13) | ... P14: =SUM(P10:P13) | R14: =SUM(E14:P14) | X14: =R14/$C$3 | Y14: =R14/$C$3/12
A15: 5017 | B15: CONCESSIONS
A16: 5018 | B16: BOND CONCESSION | R16: =SUM(E16:P16) | X16: =R16/$C$3 | Y16: =R16/$C$3/12
A17: 5019 | B17: PEP CONCESSION | D17: UW cat 2 share | E17: -752.23 | F17: -752.23 | G17: -752.24 | H17: -752.24 | I17: -752.24 | J17: -752.24 | K17: -752.24 | L17: -752.24 | M17: -752.24 | N17: -752.24 | O17: -752.24 | P17: -752.24 | R17: =SUM(E17:P17) | U17: -5284.68 | X17: =R17/$C$3 | Y17: =R17/$C$3/12
A18: 5020 | B18: RENT CONCESSION - RECURRING | D18: UW cat 2 share | E18: -192.41 | F18: -192.41 | G18: -192.41 | H18: -192.41 | I18: -192.42 | J18: -192.42 | K18: -192.42 | L18: -192.42 | M18: -192.42 | N18: -192.42 | O18: -192.42 | P18: -192.42 | R18: =SUM(E18:P18) | U18: -1351.78 | X18: =R18/$C$3 | Y18: =R18/$C$3/12
A19: 5021 | B19: RENT CONCESSION - ONE-TIME | D19: UW cat 2 share | E19: -59.86 | F19: -59.86 | G19: -59.86 | H19: -59.86 | I19: -59.86 | J19: -59.86 | K19: -59.86 | L19: -59.86 | M19: -59.86 | N19: -59.86 | O19: -59.86 | P19: -59.87 | R19: =SUM(E19:P19) | U19: -420.54 | X19: =R19/$C$3 | Y19: =R19/$C$3/12
A20: 5022 | B20: CONCESSION RECAPTURE | R20: =SUM(E20:P20) | X20: =R20/$C$3 | Y20: =R20/$C$3/12
A21: 5023 | B21: RENEWAL CONCESSION | R21: =SUM(E21:P21) | X21: =R21/$C$3 | Y21: =R21/$C$3/12
A22: 5024 | B22: MOVE-IN CONCESSION | D22: UW cat 2 share | E22: -182.48 | F22: -182.48 | G22: -182.48 | H22: -182.49 | I22: -182.49 | J22: -182.49 | K22: -182.49 | L22: -182.49 | M22: -182.49 | N22: -182.49 | O22: -182.49 | P22: -182.49 | R22: =SUM(E22:P22) | U22: -1282.02 | X22: =R22/$C$3 | Y22: =R22/$C$3/12
A23: 5025 | B23: REFERRAL CONCESSION | D23: UW cat 2 share | E23: -195.52 | F23: -195.52 | G23: -195.52 | H23: -195.52 | I23: -195.52 | J23: -195.52 | K23: -195.52 | L23: -195.52 | M23: -195.52 | N23: -195.52 | O23: -195.53 | P23: -195.53 | R23: =SUM(E23:P23) | U23: -1373.6 | X23: =R23/$C$3 | Y23: =R23/$C$3/12
A24: 5027 | B24: SUMMER STORAGE CONCESSION | R24: =SUM(E24:P24) | X24: =R24/$C$3 | Y24: =R24/$C$3/12
A25: 5028 | B25: FIRE CONCESSION | R25: =SUM(E25:P25) | X25: =R25/$C$3 | Y25: =R25/$C$3/12
A26: 5029 | B26: TOTAL CONCESSIONS | E26: =SUM(E16:E25) | F26: =SUM(F16:F25) | G26: =SUM(G16:G25) | H26: =SUM(H16:H25) | I26: =SUM(I16:I25) | J26: =SUM(J16:J25) | K26: =SUM(K16:K25) | L26: =SUM(L16:L25) | ... P26: =SUM(P16:P25) | R26: =SUM(E26:P26) | T26: -16095.465 | X26: =R26/$C$3 | Y26: =R26/$C$3/12
A27: 5030 | B27: RENTAL LOSS
A28: 5031 | B28: Less: VACANCY | D28: vacancy % of GPR | E28: -13825.25 | F28: -13825.25 | G28: -13825.25 | H28: -13825.25 | I28: -13825.25 | J28: -13825.25 | K28: -13825.25 | L28: -13825.25 | M28: -13825.25 | N28: -13825.25 | O28: -13825.25 | P28: -13825.25 | R28: =SUM(E28:P28) | U28: -78107.05 | X28: =R28/$C$3 | Y28: =R28/$C$3/12
A29: 5032 | B29: Less: MODELS | R29: =SUM(E29:P29) | X29: =R29/$C$3 | Y29: =R29/$C$3/12
A30: 5033 | B30: Less: ADMIN | R30: =SUM(E30:P30) | U30: -3021.91 | X30: =R30/$C$3 | Y30: =R30/$C$3/12
A31: 5034 | B31: Less: DOWN | R31: =SUM(E31:P31) | X31: =R31/$C$3 | Y31: =R31/$C$3/12
A32: 5035 | B32: Less: CURRENT DELINQUENCY | R32: =SUM(E32:P32) | U32: -6294.37 | X32: =R32/$C$3 | Y32: =R32/$C$3/12
A33: 5036 | B33: PRIOR PERIOD COLLECTIONS | R33: =SUM(E33:P33) | U33: 4586.33 | X33: =R33/$C$3 | Y33: =R33/$C$3/12
A34: 5040 | B34: WRITE-OFFS | R34: =SUM(E34:P34) | X34: =R34/$C$3 | Y34: =R34/$C$3/12
A35: 5049 | B35: TOTAL RENTAL LOSS | E35: =SUM(E28:E34) | F35: =SUM(F28:F34) | G35: =SUM(G28:G34) | H35: =SUM(H28:H34) | I35: =SUM(I28:I34) | J35: =SUM(J28:J34) | K35: =SUM(K28:K34) | L35: =SUM(L28:L34) | ... P35: =SUM(P28:P34) | R35: =SUM(E35:P35) | T35: -160954.65 | X35: =R35/$C$3 | Y35: =R35/$C$3/12
A36: 5070 | B36: TOTAL RENTAL INCOME | E36: =E14+E26+E35 | F36: =F14+F26+F35 | G36: =G14+G26+G35 | H36: =H14+H26+H35 | I36: =I14+I26+I35 | J36: =J14+J26+J35 | K36: =K14+K26+K35 | L36: =L14+L26+L35 | ... P36: =P14+P26+P35 | R36: =SUM(E36:P36) | X36: =R36/$C$3 | Y36: =R36/$C$3/12
A37: 5100 | B37: OTHER INCOME
A38: 5103 | B38: ALARM FEE | R38: =SUM(E38:P38) | X38: =R38/$C$3 | Y38: =R38/$C$3/12
A39: 5104 | B39: AMENITY MEMBERSHIP | R39: =SUM(E39:P39) | X39: =R39/$C$3 | Y39: =R39/$C$3/12
A40: 5105 | B40: APPLICATION FEES | D40: UW cat 5 share | E40: 277.81 | F40: 185.2 | G40: 155.96 | H40: 139.39 | I40: 185.2 | J40: 185.2 | K40: 321.67 | L40: 394.77 | M40: 385.03 | N40: 350.91 | O40: 341.16 | P40: 350.91 | R40: =SUM(E40:P40) | U40: 7687.56 | X40: =R40/$C$3 | Y40: =R40/$C$3/12
A41: 5110 | B41: BAD DEBT RECOVERY | D41: UW cat 5 share | E41: 174.48 | F41: 174.48 | G41: 174.48 | H41: 174.48 | I41: 203.73 | J41: 203.72 | K41: 252.46 | L41: 164.73 | M41: 164.73 | N41: 159.86 | O41: 159.86 | P41: 159.86 | R41: =SUM(E41:P41) | U41: 5089.17 | X41: =R41/$C$3 | Y41: =R41/$C$3/12
A42: 5112 | B42: CELL TOWER RENT | R42: =SUM(E42:P42) | X42: =R42/$C$3 | Y42: =R42/$C$3/12
A43: 5115 | B43: CABLE TV/INTERNET | D43: UW cat 5 share | E43: 108.2 | F43: 107.22 | G43: 110.15 | H43: 112.1 | I43: 113.07 | J43: 114.04 | K43: 112.09 | L43: 110.15 | M43: 110.15 | N43: 107.22 | O43: 107.22 | P43: 108.2 | R43: =SUM(E43:P43) | U43: 3099.75 | X43: =R43/$C$3 | Y43: =R43/$C$3/12
A44: 5116 | B44: CORPORATE FEES | R44: =SUM(E44:P44) | X44: =R44/$C$3 | Y44: =R44/$C$3/12
A45: 5117 | B45: CONVENIENCE FEE | D45: UW cat 5 share | E45: 563.41 | F45: 582.9 | G45: 592.65 | H45: 583.88 | I45: 586.8 | J45: 558.53 | K45: 558.53 | L45: 582.9 | M45: 592.65 | N45: 573.15 | O45: 568.28 | P45: 563.41 | R45: =SUM(E45:P45) | U45: 16222.16 | X45: =R45/$C$3 | Y45: =R45/$C$3/12
A46: 5118 | B46: COMMERCIAL RENT | D46: UW cat 5 share | E46: 8821.27 | F46: 8821.27 | G46: 8821.27 | H46: 8821.27 | I46: 8572.66 | J46: 8572.66 | K46: 8572.66 | L46: 8572.66 | M46: 8572.66 | N46: 8572.66 | O46: 8572.66 | P46: 8821.26 | R46: =SUM(E46:P46) | U46: 244527.08 | X46: =R46/$C$3 | Y46: =R46/$C$3/12
A47: 5119 | B47: VENDOR COMMISSIONS | R47: =SUM(E47:P47) | X47: =R47/$C$3 | Y47: =R47/$C$3/12
A48: 5120 | B48: DAMAGE REIMBURSEMENT | R48: =SUM(E48:P48) | X48: =R48/$C$3 | Y48: =R48/$C$3/12
A49: 5121 | B49: FURNITURE RENTAL INCOME | R49: =SUM(E49:P49) | X49: =R49/$C$3 | Y49: =R49/$C$3/12
A50: 5122 | B50: HAP UTILITY ALLOWANCE | R50: =SUM(E50:P50) | X50: =R50/$C$3 | Y50: =R50/$C$3/12
A51: 5124 | B51: HAP REPAYMENT EXPENSE RECOVERY | R51: =SUM(E51:P51) | X51: =R51/$C$3 | Y51: =R51/$C$3/12
A52: 5125 | B52: INTEREST INCOME | R52: =SUM(E52:P52) | X52: =R52/$C$3 | Y52: =R52/$C$3/12
A53: 5126 | B53: INSURANCE NON-COMPLIANCE FEES | D53: UW cat 5 share | E53: 232.48 | F53: 232.48 | G53: 227.61 | H53: 218.83 | I53: 196.41 | J53: 203.24 | K53: 212.98 | L53: 212.98 | M53: 208.11 | N53: 217.86 | O53: 222.73 | P53: 227.6 | R53: =SUM(E53:P53) | U53: 6137.68 | X53: =R53/$C$3 | Y53: =R53/$C$3/12
A54: 5130 | B54: OTHER MISCELLANEOUS INCOME | D54: UW cat 5 share | E54: 148.65 | F54: 148.65 | G54: 134.03 | H54: 99.91 | I54: 99.91 | J54: 109.66 | K54: 119.41 | L54: 114.53 | M54: 104.78 | N54: 124.28 | O54: 158.4 | P54: 158.4 | R54: =SUM(E54:P54) | U54: 3571.35 | X54: =R54/$C$3 | Y54: =R54/$C$3/12
A55: 5131 | B55: EQUIPMENT LEASE | R55: =SUM(E55:P55) | X55: =R55/$C$3 | Y55: =R55/$C$3/12
A56: 5132 | B56: WASHER/DRYER RENTAL INCOME | R56: =SUM(E56:P56) | X56: =R56/$C$3 | Y56: =R56/$C$3/12
A57: 5135 | B57: LAUNDRY INCOME | D57: UW cat 5 share | E57: 53.13 | F57: 53.13 | G57: 53.13 | H57: 53.13 | I57: 53.13 | J57: 53.12 | K57: 53.12 | L57: 53.12 | M57: 53.12 | N57: 53.12 | O57: 53.12 | P57: 53.12 | R57: =SUM(E57:P57) | U57: 1497.22 | X57: =R57/$C$3 | Y57: =R57/$C$3/12
A58: 5136 | B58: STORAGE UNIT INCOME | R58: =SUM(E58:P58) | X58: =R58/$C$3 | Y58: =R58/$C$3/12
A59: 5138 | B59: CLUBHOUSE RENTAL | D59: UW cat 5 share | E59: 48.25 | F59: 107.71 | G59: 152.55 | H59: 93.09 | I59: 71.65 | J59: 60.92 | K59: 48.25 | L59: 93.09 | M59: 62.87 | N59: 48.25 | O59: 77.49 | P59: 48.25 | R59: =SUM(E59:P59) | U59: 2142.81 | X59: =R59/$C$3 | Y59: =R59/$C$3/12
A60: 5140 | B60: LEASE TERMINATION | D60: UW cat 5 share | E60: 644.75 | F60: 644.75 | G60: 644.75 | H60: 644.74 | I60: 644.75 | J60: 644.74 | K60: 644.74 | L60: 644.74 | M60: 644.74 | N60: 644.74 | O60: 644.74 | P60: 644.74 | R60: =SUM(E60:P60) | U60: 18171.12 | X60: =R60/$C$3 | Y60: =R60/$C$3/12
A61: 5145 | B61: LEGAL FEES | D61: UW cat 5 share | E61: 26.81 | F61: 26.81 | G61: 26.81 | H61: 26.81 | I61: 26.81 | J61: 26.81 | K61: 26.81 | L61: 26.8 | M61: 26.8 | N61: 26.8 | O61: 26.8 | P61: 26.8 | R61: =SUM(E61:P61) | U61: 755.48 | X61: =R61/$C$3 | Y61: =R61/$C$3/12
A62: 5147 | B62: MODEL INCOME | R62: =SUM(E62:P62) | X62: =R62/$C$3 | Y62: =R62/$C$3/12
A63: 5149 | B63: HOLD OVER COMMERCIAL | R63: =SUM(E63:P63) | X63: =R63/$C$3 | Y63: =R63/$C$3/12
A64: 5150 | B64: MONTH-TO-MONTH | D64: UW cat 5 share | E64: 164.73 | F64: 164.73 | G64: 213.47 | H64: 217.37 | I64: 235.89 | J64: 232.97 | K64: 223.22 | L64: 203.72 | M64: 184.23 | N64: 184.23 | O64: 203.72 | P64: 203.72 | R64: =SUM(E64:P64) | U64: 5711.87 | X64: =R64/$C$3 | Y64: =R64/$C$3/12
A65: 5151 | B65: SHORT TERM LEASE PREMIUM | D65: UW cat 5 share | E65: 42.11 | F65: 42.11 | G65: 42.11 | H65: 42.11 | I65: 42.11 | J65: 42.11 | K65: 42.11 | L65: 42.11 | M65: 42.11 | N65: 42.11 | O65: 42.11 | P65: 42.1 | R65: =SUM(E65:P65) | U65: 1186.79 | X65: =R65/$C$3 | Y65: =R65/$C$3/12
A66: 5152 | B66: DEPOSITS FORFEITURE | D66: UW cat 5 share | E66: 1065.4 | F66: 933.81 | G66: 1070.28 | H66: 1115.12 | I66: 708.64 | J66: 709.62 | K66: 826.59 | L66: 1211.62 | M66: 1270.1 | N66: 1123.89 | O66: 1182.37 | P66: 1182.37 | R66: =SUM(E66:P66) | U66: 29122.51 | X66: =R66/$C$3 | Y66: =R66/$C$3/12
A67: 5155 | B67: NSF FEES INCOME | D67: UW cat 5 share | E67: 23.81 | F67: 23.8 | G67: 23.8 | H67: 23.8 | I67: 23.8 | J67: 23.8 | K67: 23.8 | L67: 23.8 | M67: 23.8 | N67: 23.8 | O67: 23.8 | P67: 23.8 | R67: =SUM(E67:P67) | U67: 670.78 | X67: =R67/$C$3 | Y67: =R67/$C$3/12
A68: 5156 | B68: CREDIT APPROVAL FEE | R68: =SUM(E68:P68) | X68: =R68/$C$3 | Y68: =R68/$C$3/12
A69: 5157 | B69: NON-REFUND ADMIN FEE | D69: UW cat 5 share | E69: 307.78 | F69: 237.35 | G69: 227.6 | H69: 167.17 | I69: 154.25 | J69: 173.75 | K69: 270.25 | L69: 314.11 | M69: 348.23 | N69: 359.44 | O69: 378.94 | P69: 408.18 | R69: =SUM(E69:P69) | U69: 7860.97 | X69: =R69/$C$3 | Y69: =R69/$C$3/12
A70: 5158 | B70: PEST CONTROL FEE | D70: UW cat 5 share | E70: 336.78 | F70: 336.78 | G70: 327.03 | H70: 331.9 | I70: 331.9 | J70: 336.78 | K70: 336.78 | L70: 336.78 | M70: 336.77 | N70: 331.9 | O70: 331.9 | P70: 341.65 | R70: =SUM(E70:P70) | U70: 9434.31 | X70: =R70/$C$3 | Y70: =R70/$C$3/12
A71: 5159 | B71: PARKING GARAGE-MONTHLY NON-TENANT | R71: =SUM(E71:P71) | X71: =R71/$C$3 | Y71: =R71/$C$3/12
A72: 5160 | B72: PARKING INCOME | D72: UW cat 5 share | E72: 524.42 | F72: 527.34 | G72: 518.57 | H72: 525.39 | I72: 528.32 | J72: 528.31 | K72: 528.31 | L72: 528.31 | M72: 527.34 | N72: 528.31 | O72: 522.47 | P72: 518.57 | R72: =SUM(E72:P72) | U72: 14809.65 | X72: =R72/$C$3 | Y72: =R72/$C$3/12
A73: 5161 | B73: PARKING GARAGE INCOME | R73: =SUM(E73:P73) | X73: =R73/$C$3 | Y73: =R73/$C$3/12
A74: 5162 | B74: COMMERCIAL PARKING GARAGE-OTHER | R74: =SUM(E74:P74) | X74: =R74/$C$3 | Y74: =R74/$C$3/12
A75: 5163 | B75: PAYMENT PLAN FEE | R75: =SUM(E75:P75) | X75: =R75/$C$3 | Y75: =R75/$C$3/12
A76: 5164 | B76: TRASH REIM - VALET SVC | R76: =SUM(E76:P76) | X76: =R76/$C$3 | Y76: =R76/$C$3/12
A77: 5165 | B77: PET FEE / RENT | D77: UW cat 5 share | E77: 1022.03 | F77: 1051.27 | G77: 1056.14 | H77: 1056.14 | I77: 1075.64 | J77: 1080.51 | K77: 1075.64 | L77: 1065.89 | M77: 1036.65 | N77: 1022.03 | O77: 1022.02 | P77: 1036.65 | R77: =SUM(E77:P77) | U77: 29594.12 | X77: =R77/$C$3 | Y77: =R77/$C$3/12
A78: 5166 | B78: INITIAL PET MOVE IN CHARGE | D78: UW cat 5 share | E78: 221.76 | F78: 221.76 | G78: 192.51 | H78: 153.52 | I78: 299.74 | J78: 231.5 | K78: 221.76 | L78: 260.74 | M78: 251 | N78: 231.5 | O78: 270.49 | P78: 251 | R78: =SUM(E78:P78) | U78: 6593.26 | X78: =R78/$C$3 | Y78: =R78/$C$3/12
A79: 5167 | B79: SEWER REIM | D79: UW cat 4 share | E79: 3640.96 | F79: 3837.12 | G79: 3747.52 | H79: 3232.92 | I79: 2432.56 | J79: 2633.55 | K79: 2583.91 | L79: 3261.97 | M79: 3219.6 | N79: 3242.6 | O79: 3689.4 | P79: 3585.27 | R79: =SUM(E79:P79) | U79: 36970.32 | X79: =R79/$C$3 | Y79: =R79/$C$3/12
A80: 5168 | B80: TRANSFER FEE | D80: UW cat 5 share | E80: 7.8 | F80: 7.8 | G80: 7.8 | H80: 7.8 | I80: 7.8 | J80: 7.8 | K80: 7.8 | L80: 7.8 | M80: 7.8 | N80: 7.8 | O80: 7.79 | P80: 7.79 | R80: =SUM(E80:P80) | U80: 219.78 | X80: =R80/$C$3 | Y80: =R80/$C$3/12
A81: 5169 | B81: TRASH REIM | D81: UW cat 4 share | E81: 2127.43 | F81: 1996.66 | G81: 1922.8 | H81: 1945.8 | I81: 2065.67 | J81: 1988.18 | K81: 2454.35 | L81: 2284.84 | M81: 2190.39 | N81: 2091.1 | O81: 2177.07 | P81: 2007.56 | R81: =SUM(E81:P81) | U81: 23871.95 | X81: =R81/$C$3 | Y81: =R81/$C$3/12
A82: 5170 | B82: UTILITIES REIM | D82: UW cat 4 share | E82: 1228.19 | F82: 1203.97 | G82: 1203.97 | H82: 1194.28 | I82: 1179.75 | J82: 1179.75 | K82: 1179.75 | L82: 1179.75 | M82: 1179.75 | N82: 1179.75 | O82: 1203.97 | P82: 1228.19 | R82: =SUM(E82:P82) | U82: 13557.39 | X82: =R82/$C$3 | Y82: =R82/$C$3/12
A83: 5171 | B83: GAS REIM | D83: UW cat 4 share | E83: 1437.25 | F83: 1248.37 | G83: 1078.85 | H83: 1107.91 | I83: 2149.22 | J83: 2018.45 | K83: 2569.38 | L83: 3734.2 | M83: 3100.94 | N83: 2525.79 | O83: 2111.69 | P83: 1593.45 | R83: =SUM(E83:P83) | U83: 23327.09 | X83: =R83/$C$3 | Y83: =R83/$C$3/12
A84: 5172 | B84: STREET REIM | D84: UW cat 4 share | E84: 41.17 | F84: 41.17 | G84: 41.17 | H84: 41.17 | I84: 41.17 | J84: 41.17 | K84: 41.17 | L84: 41.17 | M84: 41.17 | N84: 41.17 | O84: 41.16 | P84: 41.16 | R84: =SUM(E84:P84) | U84: 467.02 | X84: =R84/$C$3 | Y84: =R84/$C$3/12
A85: 5174 | B85: WATER REIM | D85: UW cat 4 share | E85: 3459.34 | F85: 3705.14 | G85: 3878.29 | H85: 3103.36 | I85: 2824.86 | J85: 2339.32 | K85: 2271.52 | L85: 2766.74 | M85: 2783.7 | N85: 2657.77 | O85: 3113.04 | P85: 3283.77 | R85: =SUM(E85:P85) | U85: 34209.4 | X85: =R85/$C$3 | Y85: =R85/$C$3/12
A86: 5175 | B86: VENDING MACHINES | R86: =SUM(E86:P86) | X86: =R86/$C$3 | Y86: =R86/$C$3/12
A87: 5178 | B87: VENDOR REBATES | D87: UW cat 5 share | E87: 38.04 | F87: 49.73 | G87: 53.63 | H87: 38.04 | I87: 40.96 | J87: 55.1 | K87: 41.94 | L87: 39.01 | M87: 38.04 | N87: 38.52 | O87: 39.01 | P87: 44.37 | R87: =SUM(E87:P87) | U87: 1212.8 | X87: =R87/$C$3 | Y87: =R87/$C$3/12
A88: 5180 | B88: OTHER INCOME | D88: UW cat 5 share | E88: 373.52 | F88: 373.52 | G88: 373.52 | H88: 373.52 | I88: 373.52 | J88: 373.51 | K88: 373.51 | L88: 373.51 | M88: 373.51 | N88: 373.51 | O88: 373.51 | P88: 373.51 | R88: =SUM(E88:P88) | U88: 10526.93 | X88: =R88/$C$3 | Y88: =R88/$C$3/12
A89: 5181 | B89: OTHER COMMISSION INCOME | R89: =SUM(E89:P89) | X89: =R89/$C$3 | Y89: =R89/$C$3/12
A90: 5183 | B90: COMM- CAM RECOVERY | D90: UW cat 5 share | E90: 1899.55 | F90: 1899.55 | G90: 1899.55 | H90: 1899.55 | I90: 1899.55 | J90: 1899.55 | K90: 1899.55 | L90: 1899.55 | M90: 1899.54 | N90: 1899.54 | O90: 1899.54 | P90: 1899.54 | R90: =SUM(E90:P90) | U90: 53535.88 | X90: =R90/$C$3 | Y90: =R90/$C$3/12
A91: 5184 | B91: COMM- INS RECOVERY | R91: =SUM(E91:P91) | X91: =R91/$C$3 | Y91: =R91/$C$3/12
A92: 5185 | B92: COMM - TAX RECOVERY | D92: UW cat 5 share | E92: 890.3 | F92: 890.3 | G92: 890.3 | H92: 890.3 | I92: 890.3 | J92: 890.3 | K92: 890.3 | L92: 890.3 | M92: 890.3 | N92: 890.29 | O92: 890.29 | P92: 890.29 | R92: =SUM(E92:P92) | U92: 25091.7 | X92: =R92/$C$3 | Y92: =R92/$C$3/12
A93: 5186 | B93: COMM- FIXED RECOVERY | R93: =SUM(E93:P93) | X93: =R93/$C$3 | Y93: =R93/$C$3/12
A94: 5190 | B94: NET OTHER INCOME | E94: =SUM(E38:E93) | F94: =SUM(F38:F93) | G94: =SUM(G38:G93) | H94: =SUM(H38:H93) | I94: =SUM(I38:I93) | J94: =SUM(J38:J93) | K94: =SUM(K38:K93) | L94: =SUM(L38:L93) | ... P94: =SUM(P38:P93) | R94: =SUM(E94:P94) | T94: 354851.53 | X94: =R94/$C$3 | Y94: =R94/$C$3/12
A95: 5500 | B95: TOTAL INCOME | E95: =E36+E94 | F95: =F36+F94 | G95: =G36+G94 | H95: =H36+H94 | I95: =I36+I94 | J95: =J36+J94 | K95: =K36+K94 | L95: =L36+L94 | ... P95: =P36+P94 | R95: =SUM(E95:P95) | T95: 3316417 | X95: =R95/$C$3 | Y95: =R95/$C$3/12
A96: 5999 | B96: EXPENSES
A97: 6000 | B97: OPERATING EXPENSES
A98: 6100 | B98: FIXED ADMINISTRATIVE
A99: 6102 | B99: ACCOUNTING FEES | D99: UW cat 9 share | E99: 482.13 | H99: 482.13 | K99: 482.12 | L99: 581.25 | N99: 482.12 | R99: =SUM(E99:P99) | U99: 4250.53 | X99: =R99/$C$3 | Y99: =R99/$C$3/12
A100: 6104 | B100: AUTO INSURANCE | D100: UW cat 9 share | E100: 54.52 | F100: 257.27 | G100: 54.52 | H100: 54.51 | I100: 54.51 | J100: 54.51 | K100: 54.51 | L100: 54.51 | M100: 54.51 | N100: 54.51 | O100: 54.51 | P100: 54.51 | R100: =SUM(E100:P100) | U100: 1451.23 | X100: =R100/$C$3 | Y100: =R100/$C$3/12
A101: 6108 | B101: INSURANCE EXPENSE | D101: UW cat 6 share | E101: 3871.25 | F101: 3871.25 | G101: 3871.25 | H101: 3871.25 | I101: 3871.25 | J101: 3871.25 | K101: 3871.25 | L101: 3871.25 | M101: 3871.25 | N101: 3871.25 | O101: 3871.25 | P101: 3871.25 | R101: =SUM(E101:P101) | T101: 46455 | U101: 46455 | X101: =R101/$C$3 | Y101: =R101/$C$3/12
A102: 6110 | B102: INSURANCE - FLOOD | R102: =SUM(E102:P102) | X102: =R102/$C$3 | Y102: =R102/$C$3/12
...

Sheet Summary
B1: Deer Ridge Apartments Year 1 Budget Analysis (Sep-26 – Aug-27)
G2: Unit Count | H2: 163
B4: Account Summary | D4: Year 1 UW Budget | E4: Year 1 Budget | F4: Δ vs UW | G4: Per Unit | H4: Per Unit / Month
A5: 5070 | B5: TOTAL RENTAL INCOME | D5: 2961565.5 | E5: =Budget!R36 | F5: =E5-D5 | G5: =E5/$H$2 | H5: =E5/$H$2/12
A6: 5190 | B6: NET OTHER INCOME | D6: 354851.53 | E6: =Budget!R94 | F6: =E6-D6 | G6: =E6/$H$2 | H6: =E6/$H$2/12
A7: 5500 | B7: TOTAL INCOME | D7: 3316417 | E7: =Budget!R95 | F7: =E7-D7 | G7: =E7/$H$2 | H7: =E7/$H$2/12
A8: 6170 | B8: TOTAL FIXED ADMINISTRATIVE | D8: 56633.7 | E8: =Budget!R111 | F8: =E8-D8 | G8: =E8/$H$2 | H8: =E8/$H$2/12
A9: 6370 | B9: TOTAL ADMINISTRATIVE | D9: 4491.3 | E9: =Budget!R155 | F9: =E9-D9 | G9: =E9/$H$2 | H9: =E9/$H$2/12
A10: 6399 | B10: TOTAL CORPORATE EVENTS | D10: 0 | E10: =Budget!R165 | F10: =E10-D10 | G10: =E10/$H$2 | H10: =E10/$H$2/12
A11: 6470 | B11: TOTAL PAYROLL | D11: 321925 | E11: =Budget!R185 | F11: =E11-D11 | G11: =E11/$H$2 | H11: =E11/$H$2/12
A12: 6570 | B12: TOTAL MARKETING | D12: 26895 | E12: =Budget!R206 | F12: =E12-D12 | G12: =E12/$H$2 | H12: =E12/$H$2/12
A13: 6670 | B13: TOTAL UTILITIES | D13: 188508.56 | E13: =Budget!R231 | F13: =E13-D13 | G13: =E13/$H$2 | H13: =E13/$H$2/12
A14: 6770 | B14: TOTAL IN-HOUSE MAINT | D14: 36713.51 | E14: =Budget!R255 | F14: =E14-D14 | G14: =E14/$H$2 | H14: =E14/$H$2/12
A15: 6870 | B15: TOTAL EXTERIOR/CAM | D15: 4627.82 | E15: =Budget!R270 | F15: =E15-D15 | G15: =E15/$H$2 | H15: =E15/$H$2/12
A16: 6970 | B16: TOTAL CONTRACT SERVICES | D16: 137958.68 | E16: =Budget!R297 | F16: =E16-D16 | G16: =E16/$H$2 | H16: =E16/$H$2/12
A17: 7070 | B17: TOTAL REHAB/REPLACEMENT | D17: 57050 | E17: =Budget!R315 | F17: =E17-D17 | G17: =E17/$H$2 | H17: =E17/$H$2/12
A18: 7099 | B18: TOTAL OPERATING EXPENSES | D18: 1298476.1 | E18: =Budget!R317 | F18: =E18-D18 | G18: =E18/$H$2 | H18: =E18/$H$2/12
A19: 7280 | B19: NET OPERATING INCOME | D19: 2017941 | E19: =Budget!R319 | F19: =E19-D19 | G19: =E19/$H$2 | H19: =E19/$H$2/12
B21: Interest Expense | E21: =Budget!R324
B22: Principal | E22: =ABS(Budget!R388+Budget!R389+Budget!R390)
B23: Special Projects | E23: =Budget!R376
B24: Cash Flow (NOI − debt service) | E24: =E19-E21-E22
B26: Capital Contributions | D26: 0
B27: Cash on Cash Return | E27: =IF(D26>0,E24/D26,"")

Sheet Raw Data
A1: Generated inputs (budgets.inputs)
A2: key | B2: value
A3: gpr.growthPct | B3: 0, 0, 0, 0, 0, 0, 0, 0, 0, 0, 0, 0
A4: gpr.baseMonthly | B4: 276505
A5: ltl.targetPct | B5: 0.025
A6: ltl.rampMonths | B6: 12
A7: ltl.startMonthly | B7: -26474
A8: loan | B8: 0
A9: rate | B9: 0.06
A10: year | B10: 2026
A11: units | B11: 163
A12: uwAbs.4 | B12: 140056.67
A13: uwAbs.5 | B13: 214794.86
A14: uwAbs.6 | B14: 46455
A15: uwAbs.8 | B15: 317725
... A21: uwAbs.14 | B21: 57050
A22: tieNoi | B22: TRUE
A23: capital | B23: 0
A24: mgmtPct | B24: 0.03
A25: tieIncome | B25: TRUE
A26: startMonth | B26: 9
A27: vacancyPct | B27: 0.05, 0.05, 0.05, 0.05, 0.05, 0.05, 0.05, 0.05, 0.05, 0.05, 0.05, 0.05
A28: concessionPct | B28: 0.005
A29: rentalLossPct | B29: 0.05
A31: UW Year-1 by category (tie-out targets)
A32: pcode | B32: label | C32: UW Y1
A33: 1 | B33: Gross Potential Rent | C33: 3219092.9
A34: loss | B34: Loss to Lease | C34: -80477.323
A35: 2 | B35: Concessions | C35: -16095.465
A36: 3 | B36: Rental Loss (Vacancy etc.) | C36: -160954.65
A37: 4 | B37: Utility Income | C37: 140056.67
A38: 5 | B38: Other Income | C38: 214794.86
A39: 6 | B39: Insurance | C39: 46455
A40: 7 | B40: Management Fee | C40: 99492.511
A41: 8 | B41: RE & PP Taxes | C41: 317725
A42: 9 | B42: Admin & Accounting | C42: 61125
A43: 10 | B43: Payroll & Benefits | C43: 321925
A44: 11 | B44: Marketing | C44: 26895
... A47: 14 | B47: Rehab / Reserves | C47: 57050
B48: EGI | C48: 3316417
B49: TOE | C49: 1298476.1
B50: NOI | C50: 2017941
A52: Comp set: Minot 4 12-Month Budget 2026 (Cash) (annual $, 712 units)
A53: gl | B53: comp annual $ | C53: comp $/unit | D53: scaled to 163 units
A54: 3080 | B54: -298232.69 | C54: -418.87 | D54: -68275.18
A55: 4994 | B55: 12274766 | C55: 17239.84 | D55: 2810093.9
A56: 4996 | B56: 116160 | C56: 163.15 | D56: 26592.81
A57: 5003 | B57: -1644628.7 | C57: -2309.87 | D57: -376509.1
A58: 5004 | B58: 10746297 | C58: 15093.11 | D58: 2460177.6
A59: 5019 | B59: -23084.01 | C59: -32.42 | D59: -5284.68
A60: 5020 | B60: -5904.72 | C60: -8.29 | D60: -1351.78
A61: 5021 | B61: -1836.96 | C61: -2.58 | D61: -420.54
A62: 5024 | B62: -5600 | C62: -7.87 | D62: -1282.02
A63: 5025 | B63: -6000 | C63: -8.43 | D63: -1373.6
A64: 5029 | B64: -42425.69 | C64: -59.59 | D64: -9712.62
A65: 5031 | B65: -341179.27 | C65: -479.18 | D65: -78107.05
... A252: 9000 | B252: 1641610.9 | C252: 2305.63 | D252: 375818.22
A254: Budget lines (raw)
A255: gl | B255: annual | C255: override | D255: driver json
A256: 4994 | B256: 3318060 | D256: {"method":"gpr"}
A257: 5003 | B257: -174001.2 | D257: {"method":"ltl"}
A258: 5019 | B258: -9026.86 | D258: {"pcode":"2","share":0.5441046876789449,"method":"catShare"}
A259: 5020 | B259: -2309 | D259: {"pcode":"2","share":0.13917771227765624,"method":"catShare"}
A260: 5021 | B260: -718.33 | D260: {"pcode":"2","share":0.0432981923171974,"method":"catShare"}
A261: 5024 | B261: -2189.85 | D261: {"pcode":"2","share":0.13199580477749046,"method":"catShare"}
A262: 5025 | B262: -2346.26 | D262: {"pcode":"2","share":0.141423602948711,"method":"catShare"}
A263: 5031 | B263: -165903 | D263: {"method":"vacancy"}
A264: 5105 | B264: 3273.21 | D264: {"pcode":"5","share":0.015238772473419523,"method":"catShare"}
A265: 5110 | B265: 2166.87 | D265: {"pcode":"5","share":0.010088090562316063,"method":"catShare"}
A266: 5115 | B266: 1319.81 | D266: {"pcode":"5","share":0.006144513886412366,"method":"catShare"}
A267: 5117 | B267: 6907.09 | D267: {"pcode":"5","share":0.03215668196157022,"method":"catShare"}
... A408: 7018 | B408: 100.31 | D408: {"pcode":"14","share":0.002662751971954426,"method":"catShare"}
